Metadata-Version: 1.0
Name: taffrail
Version: 0.6.5
Summary: An aggregate metrics python client for Kubernetes
Home-page: https://github.com/taffrailmetrics/taffrail
Author: Taffrail
Author-email: UNKNOWN
License: UNKNOWN
Keywords: Kubernetes,logging,metrics
Platform: UNKNOWN
